cerberus_api_client/__init__.py
cerberus_api_client/client.py
cerberus_api_client-1.0.0.dist-info/LICENSE
cerberus_api_client-1.0.0.dist-info/METADATA
cerberus_api_client-1.0.0.dist-info/WHEEL
cerberus_api_client-1.0.0.dist-info/top_level.txt
cerberus_api_client-1.0.0.dist-info/RECORD
