Metadata-Version: 2.1
Name: cerberus-api-client
Version: 1.0.0
Summary: A Python package to scrape OpenShift/Kubernetes cluster failures
Home-page: https://github.com/openshift-scale/cerberus-api-client
Author: Yashashree Suresh
Author-email: ysuresh@redhat.com
License: mit
Platform: UNKNOWN
Classifier: Development Status :: 4 - Beta
Classifier: Programming Language :: Python
Classifier: Programming Language :: Python :: 3
